res_address/__init__.py
res_address-2.0.0.dist-info/COPYING
res_address-2.0.0.dist-info/COPYING.LESSER
res_address-2.0.0.dist-info/METADATA
res_address-2.0.0.dist-info/WHEEL
res_address-2.0.0.dist-info/top_level.txt
res_address-2.0.0.dist-info/RECORD
