Metadata-Version: 2.1
Name: res-address
Version: 2.0.0
Summary: Simple Resource Address Parser.
Home-page: https://github.com/mrsarm/python-res-address
Download-URL: https://github.com/mrsarm/python-res-address/tarball/2.0.0
Author: Mariano Ruiz
Author-email: mrsarm@gmail.com
License: LGPL-3
Platform: any
Classifier: Intended Audience :: Developers
Classifier: License :: Public Domain
Classifier: License :: OSI Approved :: GNU Lesser General Public License v3 or later (LGPLv3+)
Classifier: Operating System :: OS Independent
Classifier: Programming Language :: Python
Classifier: Topic :: Database
Classifier: Topic :: System :: Networking
License-File: COPYING
License-File: COPYING.LESSER
